{"name": "songData", "children": [{"name": "The Kinks", "children": [{"name": "Lola", "value": 1}, {"name": "A Well Respected Man", "value": 1}, {"name": "Supersonic Rocket Ship", "value": 1}, {"name": "The Contenders - 2014 Remastered Version", "value": 1}, {"name": "Hot Potatoes", "value": 1}, {"name": "Lola - Coca Cola Version", "value": 2}, {"name": "Picture Book - 2018 Stereo Remaster", "value": 1}, {"name": "You Really Got Me - Mono Mix", "value": 2}, {"name": "Strangers", "value": 3}, {"name": "All Day and All of the Night", "value": 1}]}, {"name": "The Cure", "children": [{"name": "Close To Me", "value": 1}, {"name": "Plainsong", "value": 2}]}, {"name": "Dexys Midnight Runners", "children": [{"name": "Come On Eileen", "value": 9}]}, {"name": "a-ha", "children": [{"name": "Take on Me - Kygo Remix", "value": 1}]}, {"name": "Iggy Pop", "children": [{"name": "La Vie En Rose", "value": 1}, {"name": "The Passenger", "value": 2}, {"name": "Lust For Life", "value": 1}]}, {"name": "The Durutti Column", "children": [{"name": "Otis", "value": 1}]}, {"name": "The Clash", "children": [{"name": "Rock the Casbah - Remastered", "value": 6}, {"name": "Police & Thieves - Remastered", "value": 8}, {"name": "Lost in the Supermarket - Remastered", "value": 1}, {"name": "London Calling - Remastered", "value": 1}]}, {"name": "Lou Reed", "children": [{"name": "Perfect Day", "value": 1}, {"name": "Walk On the Wild Side", "value": 3}, {"name": "Charleys Girl", "value": 3}, {"name": "Coney Island Baby", "value": 1}, {"name": "New Sensations", "value": 1}]}, {"name": "Brian Eno", "children": [{"name": "Emerald and Stone", "value": 1}, {"name": "Ill Come Running - 2004 Digital Remaster", "value": 2}]}, {"name": "Talking Heads", "children": [{"name": "The Big Country - 2005 Remaster", "value": 5}, {"name": "Psycho Killer - 2005 Remaster", "value": 2}, {"name": "This Must Be the Place (Naive Melody) - 2005 Remaster", "value": 8}, {"name": "Burning Down the House", "value": 2}, {"name": "Once in a Lifetime - 2005 Remaster", "value": 2}, {"name": "Take Me to the River - 2005 Remaster", "value": 1}, {"name": "Making Flippy Floppy", "value": 1}, {"name": "This Must Be the Place (Naive Melody)", "value": 1}, {"name": "Pull up the Roots", "value": 1}, {"name": "Road to Nowhere", "value": 2}]}, {"name": "The Police", "children": [{"name": "Roxanne - Remastered 2003", "value": 2}]}, {"name": "T. Rex", "children": [{"name": "Bang a Gong (Get It On) - Remastered Version", "value": 2}, {"name": "Buick McCane", "value": 1}]}, {"name": "Men At Work", "children": [{"name": "Down Under", "value": 1}]}, {"name": "Pavement", "children": [{"name": "Harness Your Hopes - (B-side)", "value": 4}, {"name": "Father to a Sister of Thought", "value": 2}, {"name": "Range Life", "value": 10}, {"name": "Cut Your Hair", "value": 2}, {"name": "Gold Soundz", "value": 2}, {"name": "Gold Soundz (Remastered)", "value": 1}, {"name": "Starlings of the Slipstream", "value": 1}, {"name": "Stereo", "value": 2}, {"name": "Grave Architecture", "value": 1}, {"name": "Grounded", "value": 1}]}, {"name": "Rick Springfield", "children": [{"name": "Jessies Girl", "value": 1}]}, {"name": "Galaxie 500", "children": [{"name": "Dont Let Our Youth Go to Waste", "value": 1}, {"name": "Tugboat", "value": 2}, {"name": "Blue Thunder", "value": 1}]}, {"name": "David Bowie", "children": [{"name": "Starman - 2012 Remaster", "value": 1}, {"name": "Fame - 1999 Remaster", "value": 1}, {"name": "Right - Alternative Gouster Mix", "value": 1}, {"name": "Young Americans - 2016 Remaster", "value": 1}, {"name": "Moonage Daydream - 2012 Remaster", "value": 1}]}, {"name": "Pretenders", "children": [{"name": "Roadie Man", "value": 1}]}, {"name": "Joy Division", "children": [{"name": "Love Will Tear Us Apart - 2010 Remaster", "value": 3}, {"name": "Warsaw - 2010 Remaster", "value": 1}, {"name": "Failures - 2010 Remaster", "value": 1}]}, {"name": "Stereolab", "children": [{"name": "Brakhage", "value": 1}, {"name": "Lo Boob Oscillator", "value": 2}]}, {"name": "Sonic Youth", "children": [{"name": "The Diamond Sea - Radio Edit", "value": 1}]}, {"name": "The Replacements", "children": [{"name": "Swingin Party - 2008 Remaster", "value": 3}, {"name": "Mr. Whirly", "value": 2}]}, {"name": "The Stooges", "children": [{"name": "I Wanna Be Your Dog", "value": 1}, {"name": "Search and Destroy - Iggy Pop Mix", "value": 1}]}, {"name": "Love", "children": [{"name": "Alone Again Or - 2015 Remaster", "value": 1}, {"name": "Always See Your Face", "value": 2}]}, {"name": "Television", "children": [{"name": "Marquee Moon (Edit)", "value": 1}, {"name": "See No Evil", "value": 2}]}, {"name": "Morrissey", "children": [{"name": "Well Let You Know - 2014 Remaster", "value": 1}]}, {"name": "The Modern Lovers", "children": [{"name": "Hospital", "value": 1}, {"name": "Pablo Picasso", "value": 2}]}, {"name": "John Cale", "children": [{"name": "Paris 1919", "value": 3}]}, {"name": "XTC", "children": [{"name": "Making Plans For Nigel", "value": 1}]}, {"name": "Pulp", "children": [{"name": "Mile End", "value": 1}]}, {"name": "Blur", "children": [{"name": "Ghost Ship", "value": 1}]}, {"name": "Cocteau Twins", "children": [{"name": "Cherry-coloured Funk", "value": 2}]}, {"name": "Jonathan Richman", "children": [{"name": "You Cant Talk To The Dude", "value": 1}]}, {"name": "The Cleaners From Venus", "children": [{"name": "Only a Shadow", "value": 1}]}, {"name": "The Smiths", "children": [{"name": "This Night Has Opened My Eyes - 2011 Remaster", "value": 1}]}, {"name": "The Specials", "children": [{"name": "Ghost Town", "value": 1}]}]}