{"name": "songData", "children": [{"name": "Kurt Vile", "children": [{"name": "Thats Life, tho (almost hate to say)", "value": 1}, {"name": "Dust Bunnies", "value": 2}, {"name": "Wheelhouse", "value": 1}, {"name": "Im an Outlaw", "value": 1}, {"name": "Pretty Pimpin", "value": 14}, {"name": "Life Like This", "value": 1}, {"name": "Wakin on a Pretty Day", "value": 3}, {"name": "Lost my Head there", "value": 1}, {"name": "All in a Daze Work", "value": 1}, {"name": "One Trick Ponies", "value": 1}]}, {"name": "Sufjan Stevens", "children": [{"name": "John My Beloved", "value": 3}, {"name": "Carol of St. Benjamin The Bearded One", "value": 1}, {"name": "Fourth of July", "value": 3}, {"name": "How Shall I Fitly Meet Thee?", "value": 1}, {"name": "Hark! The Herald Angels Sing", "value": 1}, {"name": "Silent Night", "value": 1}, {"name": "Should Have Known Better", "value": 5}, {"name": "The Dress Looks Nice on You", "value": 2}, {"name": "Christ The Lord Is Born", "value": 1}, {"name": "To Be Alone With You", "value": 2}, {"name": "Ding-a-ling-a-ring-a-ling", "value": 1}, {"name": "Carrie & Lowell", "value": 4}, {"name": "No Shade in the Shadow of The Cross", "value": 3}, {"name": "Death with Dignity", "value": 5}, {"name": "All the Trees of the Field Will Clap Their Hands", "value": 3}, {"name": "Chicago", "value": 17}, {"name": "In the Devils Territory", "value": 1}, {"name": "Rake", "value": 1}, {"name": "Drawn to the Blood", "value": 3}, {"name": "The Only Thing", "value": 5}, {"name": "Casimir Pulaski Day", "value": 7}, {"name": "To The Workers of The Rock River Valley Region, I have an idea concerning your predicament, and it involves an inner tube, bath mats, and 21 able-bodied men", "value": 3}, {"name": "Concerning the UFO sighting near Highland, Illinois", "value": 4}, {"name": "The Black Hawk War, Or, How to Demolish an Entire Civilization and Still Feel Good About Yourself In the Morning, Or, We Apologize for the Inconvenience But Youre Going to Have to Leave Now, Or...", "value": 3}, {"name": "Come On! Feel the Illinoise! Part I: The Worlds Columbian Exposition Part II: Carl Sandburg Visits Me In A Dream", "value": 3}, {"name": "John Wayne Gacy, Jr.", "value": 4}, {"name": "Jacksonville", "value": 3}, {"name": "A short reprise for Mary Todd, who went insane, but for very good reasons", "value": 3}, {"name": "Decatur, or, Round of Applause for Your Step-Mother!", "value": 3}, {"name": "One last Whoo-hoo! for the Pullman", "value": 3}, {"name": "Romulus", "value": 1}, {"name": "Mystery of Love (From the Original Motion Picture \u201cCall Me by Your Name\u201d)", "value": 2}, {"name": "Futile Devices", "value": 2}, {"name": "Wallowa Lake Monster", "value": 2}, {"name": "City of Roses", "value": 2}, {"name": "Enchanting Ghost", "value": 1}, {"name": "Redford (for Yia-Yia and Pappou)", "value": 1}, {"name": "Seven Swans", "value": 1}, {"name": "The Predatory Wasp of The Palisades Is Out To Get Us", "value": 3}, {"name": "The Mistress Witch from McClure (or, The Mind That Knows Itself)", "value": 1}, {"name": "The Owl And The Tanager", "value": 1}, {"name": "The Greatest Gift", "value": 1}, {"name": "Lonely Man of Winter - Doveman Mix", "value": 1}, {"name": "Vesuvius", "value": 1}, {"name": "All of Me Wants All of You", "value": 3}, {"name": "Heirloom", "value": 1}, {"name": "The Man of Metropolis Steals Our Hearts", "value": 2}, {"name": "Prairie Fire That Wanders About", "value": 2}, {"name": "A conjunction of drones simulating the way in which Sufjan Stevens has an existential crisis in the Great Godfrey Maze", "value": 3}, {"name": "They Are Night Zombies!! They Are Neighbors!! They Have Come Back From the Dead!! Ahhhh!", "value": 2}, {"name": "Lets hear that string part again, because I dont think they heard it all the way out in Bushnell", "value": 1}, {"name": "In This Temple As in The Hearts of Man For Whom He Saved The Earth", "value": 1}, {"name": "The Seers Tower", "value": 2}, {"name": "The Tallest Man, the Broadest Shoulders Part I: The Great Frontier Part II: Come to Me Only With Playthings Now", "value": 2}, {"name": "Riffs and Variations on a single note for Jelly Roll, Earl Hines, Louis Armstrong, Baby Dodds, and the King of Swing, to name a few", "value": 1}, {"name": "Out of Egypt, into the Great Laugh of Mankind, and I shake the dirt from my sandals as I run", "value": 1}, {"name": "Blue Bucket of Gold", "value": 2}, {"name": "Eugene", "value": 2}, {"name": "Hotline Bling (Encore) - Live", "value": 2}]}, {"name": "Phosphorescent", "children": [{"name": "Song For Zula", "value": 1}]}, {"name": "Destroyer", "children": [{"name": "Blue Eyes", "value": 1}, {"name": "Chinatown", "value": 1}, {"name": "Painter in Your Pocket", "value": 5}, {"name": "Rubies", "value": 2}, {"name": "Its Gonna Take an Airplane", "value": 1}, {"name": "Crimson Tide", "value": 1}]}, {"name": "The Durutti Column", "children": [{"name": "Otis", "value": 1}]}, {"name": "Thee Oh Sees", "children": [{"name": "The Dream", "value": 1}, {"name": "Floods New Light", "value": 1}]}, {"name": "Chris Forsyth", "children": [{"name": "High Castle Rock", "value": 1}]}, {"name": "Cat Power", "children": [{"name": "Sea of Love", "value": 1}]}, {"name": "Beach House", "children": [{"name": "PPP", "value": 21}, {"name": "Sparks", "value": 28}, {"name": "Used to Be", "value": 4}, {"name": "Real Love", "value": 3}, {"name": "All Your Yeahs", "value": 4}, {"name": "Wedding Bell", "value": 4}, {"name": "Better Times", "value": 4}, {"name": "Days of Candy", "value": 20}, {"name": "Lover of Mine", "value": 4}, {"name": "Space Song", "value": 47}, {"name": "Other People", "value": 5}, {"name": "10:37", "value": 20}, {"name": "Lazuli", "value": 14}, {"name": "Levitation", "value": 35}, {"name": "Elegy to the Void", "value": 4}, {"name": "Somewhere Tonight", "value": 6}, {"name": "Wild", "value": 6}, {"name": "Bluebird", "value": 21}, {"name": "Beyond Love", "value": 20}, {"name": "Wildflower", "value": 19}, {"name": "Shes So Lovely", "value": 3}, {"name": "Rough Song", "value": 2}, {"name": "One Thing", "value": 3}, {"name": "The Hours", "value": 3}, {"name": "Irene", "value": 3}, {"name": "On the Sea", "value": 3}, {"name": "New Year", "value": 3}, {"name": "Myth", "value": 17}, {"name": "Troublemaker", "value": 1}, {"name": "Wishes", "value": 2}, {"name": "Zebra", "value": 7}, {"name": "10 Mile Stereo", "value": 3}, {"name": "Silver Soul", "value": 6}, {"name": "Take Care", "value": 10}, {"name": "You Came To Me", "value": 4}, {"name": "Saltwater", "value": 5}, {"name": "Turtle Island", "value": 3}, {"name": "Auburn And Ivory", "value": 1}, {"name": "Walk in the Park", "value": 5}, {"name": "Norway", "value": 2}, {"name": "Childhood", "value": 2}, {"name": "Tokyo Witch", "value": 2}, {"name": "The Traveller", "value": 4}, {"name": "Holy Dances", "value": 3}, {"name": "Gila", "value": 5}, {"name": "The Arrangement", "value": 3}, {"name": "Wherever You Go", "value": 1}, {"name": "Chariot", "value": 6}, {"name": "Saturn Song", "value": 3}, {"name": "10 Mile Stereo - Cough Syrup Remix", "value": 1}, {"name": "Used to Be - 2008 Single Version", "value": 3}, {"name": "Baseball Diamond", "value": 4}, {"name": "I Do Not Care for the Winter Sun", "value": 3}, {"name": "Play the Game", "value": 3}, {"name": "Baby", "value": 6}, {"name": "White Moon - iTunes Session Remix", "value": 5}, {"name": "Equal Mind", "value": 7}, {"name": "Rain in Numbers", "value": 2}, {"name": "Norway - iTunes Session Remix", "value": 3}, {"name": "Majorette", "value": 4}, {"name": "Common Girl", "value": 2}, {"name": "Heart of Chambers", "value": 4}, {"name": "Master of None", "value": 20}, {"name": "Pay No Mind", "value": 24}, {"name": "Dark Spring", "value": 22}, {"name": "LInconnue", "value": 18}, {"name": "Drunk In LA", "value": 26}, {"name": "Last Ride", "value": 14}, {"name": "Lose Your Smile", "value": 33}, {"name": "Black Car", "value": 22}, {"name": "Girl Of The Year", "value": 14}, {"name": "Lemon Glow", "value": 24}, {"name": "Woo", "value": 18}, {"name": "Dive", "value": 37}, {"name": "All The Years", "value": 2}, {"name": "Some Things Last a Long Time", "value": 2}, {"name": "Astronaut", "value": 2}, {"name": "D.A.R.L.I.N.G.", "value": 2}, {"name": "Home Again", "value": 3}, {"name": "Apple Orchard", "value": 1}, {"name": "Auburn and Ivory", "value": 2}]}, {"name": "Nick Drake", "children": [{"name": "Fly", "value": 5}]}, {"name": "Fleet Foxes", "children": [{"name": "Blue Spotted Tail", "value": 1}, {"name": "Mykonos", "value": 2}, {"name": "White Winter Hymnal", "value": 2}, {"name": "Third of May / \u014cdaigahara - Edit", "value": 2}, {"name": "Fools Errand", "value": 1}, {"name": "Sun It Rises", "value": 1}, {"name": "Ragged Wood", "value": 6}, {"name": "Tiger Mountain Peasant Song", "value": 1}, {"name": "Quiet Houses", "value": 1}, {"name": "He Doesnt Know Why", "value": 1}, {"name": "Heard Them Stirring", "value": 1}, {"name": "Your Protector", "value": 1}, {"name": "Meadowlarks", "value": 1}, {"name": "Blue Ridge Mountains", "value": 2}, {"name": "Oliver James", "value": 3}, {"name": "Battery Kinzie", "value": 1}]}, {"name": "Timber Timbre", "children": [{"name": "Hot Dreams", "value": 1}]}, {"name": "Bill Fay", "children": [{"name": "The Healing Day", "value": 1}]}, {"name": "Menomena", "children": [{"name": "Lets All Unite!", "value": 1}]}, {"name": "The Books", "children": [{"name": "That Right Aint Shit", "value": 1}]}, {"name": "Tune-Yards", "children": [{"name": "Manchild", "value": 1}]}, {"name": "Foxygen", "children": [{"name": "Shuggie", "value": 34}, {"name": "On Blue Mountain", "value": 18}, {"name": "San Francisco", "value": 29}, {"name": "Follow the Leader", "value": 15}, {"name": "Avalon", "value": 7}, {"name": "How Can You Really", "value": 1}, {"name": "No Destruction", "value": 4}, {"name": "Cosmic Vibrations", "value": 3}, {"name": "In the Darkness", "value": 19}, {"name": "Bowling Trophies", "value": 7}, {"name": "Oh Yeah", "value": 7}, {"name": "Wallys Farm", "value": 2}, {"name": "Star Power I: Overture", "value": 1}, {"name": "Make It Known", "value": 2}, {"name": "The Game", "value": 1}, {"name": "Oh No", "value": 6}, {"name": "Cant Contextualize My Mind", "value": 1}, {"name": "Take The Kids Off Broadway", "value": 3}, {"name": "America", "value": 2}, {"name": "Abandon My Toys", "value": 1}, {"name": "Teenage Alien Blues", "value": 1}, {"name": "Waitin 4 U", "value": 1}, {"name": "Middle School Dance (Song For Richard Swift)", "value": 1}, {"name": "Why Did I Get Married?", "value": 1}, {"name": "We Are the 21st Century Ambassadors of Peace & Magic", "value": 4}, {"name": "Mrs. Adams", "value": 2}, {"name": "On Lankershim", "value": 2}, {"name": "Star Power Airlines", "value": 1}, {"name": "Wheres the Money?", "value": 1}, {"name": "You & I", "value": 1}, {"name": "Livin a Lie", "value": 2}, {"name": "Face The Facts", "value": 1}, {"name": "Work", "value": 2}, {"name": "Mona", "value": 1}, {"name": "Seeing Other People", "value": 2}, {"name": "Face the Facts", "value": 2}, {"name": "The Thing Is", "value": 1}, {"name": "News", "value": 1}, {"name": "Flag at Half-Mast", "value": 1}, {"name": "The Conclusion", "value": 1}]}, {"name": "Animal Collective", "children": [{"name": "Mountain Game", "value": 1}, {"name": "What Would I Want? Sky", "value": 3}, {"name": "My Girls", "value": 3}, {"name": "Man Of Oil", "value": 1}, {"name": "Summertime Clothes", "value": 1}]}, {"name": "Kevin Morby", "children": [{"name": "I Have Been to the Mountain", "value": 1}, {"name": "City Music", "value": 2}, {"name": "Come to Me Now", "value": 2}, {"name": "Harlem River", "value": 2}, {"name": "No Halo", "value": 5}, {"name": "1234", "value": 2}, {"name": "Dry Your Eyes", "value": 1}]}, {"name": "Grizzly Bear", "children": [{"name": "Two Weeks", "value": 17}, {"name": "Deep Blue Sea - Daniel Rossen Home Recording", "value": 1}, {"name": "Hold Still", "value": 1}, {"name": "Knife", "value": 1}, {"name": "Ready, Able", "value": 4}, {"name": "Losing All Sense", "value": 5}, {"name": "Wasted Acres", "value": 2}, {"name": "Yet Again", "value": 1}]}, {"name": "Father John Misty", "children": [{"name": "Real Love Baby", "value": 47}, {"name": "Total Entertainment Forever", "value": 22}, {"name": "The Night Josh Tillman Came To Our Apt.", "value": 3}, {"name": "Pure Comedy", "value": 10}, {"name": "Nancy From Now On", "value": 10}, {"name": "Holy Shit", "value": 6}, {"name": "A Bigger Paper Bag", "value": 6}, {"name": "The Memo", "value": 9}, {"name": "Two Wildly Different Perspectives", "value": 6}, {"name": "Leaving LA", "value": 7}, {"name": "Birdie", "value": 11}, {"name": "Ballad of the Dying Man", "value": 26}, {"name": "I Went To The Store One Day", "value": 3}, {"name": "When the God of Love Returns Therell Be Hell to Pay", "value": 8}, {"name": "So Im Growing Old on Magic Mountain", "value": 5}, {"name": "In Twenty Years or So", "value": 6}, {"name": "True Affection", "value": 3}, {"name": "Smoochie", "value": 5}, {"name": "Bored In The USA", "value": 2}, {"name": "I Love You, Honeybear", "value": 6}, {"name": "Nothing Good Ever Happens At The Goddamn Thirsty Crow", "value": 1}, {"name": "The Ideal Husband", "value": 2}, {"name": "Chateau Lobby #4 (in C for Two Virgins)", "value": 5}, {"name": "Things It Would Have Been Helpful to Know Before the Revolution", "value": 12}, {"name": "Strange Encounter", "value": 1}, {"name": "When Youre Smiling And Astride Me", "value": 2}, {"name": "Hangout at the Gallows", "value": 27}, {"name": "Mr. Tillman", "value": 27}, {"name": "Just Dumb Enough to Try", "value": 5}, {"name": "Date Night", "value": 12}, {"name": "Please Dont Die", "value": 8}, {"name": "The Palace", "value": 13}, {"name": "Disappointing Diamonds Are the Rarest of Them All", "value": 7}, {"name": "Gods Favorite Customer", "value": 12}, {"name": "The Songwriter", "value": 8}, {"name": "Were Only People (And Theres Not Much Anyone Can Do About That)", "value": 9}, {"name": "Mr. Tillman - Recorded at Spotify Studios NYC", "value": 2}, {"name": "Im Writing a Novel - Spotify Sessions Curated by Jim Eno", "value": 1}, {"name": "Hollywood Forever Cemetery Sings", "value": 2}, {"name": "Funtimes in Babylon", "value": 2}, {"name": "Im Writing a Novel", "value": 1}, {"name": "O I Long to Feel Your Arms Around Me", "value": 1}, {"name": "Mistys Nightmares 1 & 2", "value": 1}, {"name": "Only Son of the Ladiesman", "value": 1}, {"name": "This Is Sally Hatchet", "value": 1}, {"name": "Well, You Can Do It Without Me", "value": 1}, {"name": "Now Im Learning to Love the War", "value": 2}, {"name": "Tee Pees 1-12", "value": 1}, {"name": "Everyman Needs a Companion", "value": 1}]}, {"name": "Real Estate", "children": [{"name": "Darling", "value": 35}, {"name": "Talking Backwards", "value": 30}, {"name": "Had To Hear", "value": 26}, {"name": "Stained Glass", "value": 8}, {"name": "Serve The Song", "value": 7}, {"name": "Beach Comber", "value": 11}, {"name": "Saturday", "value": 10}, {"name": "Crime", "value": 9}, {"name": "After The Moon", "value": 4}, {"name": "Two Arrows", "value": 4}, {"name": "White Light", "value": 4}, {"name": "Holding Pattern", "value": 4}, {"name": "Time", "value": 4}, {"name": "Diamond Eyes", "value": 5}, {"name": "Same Sun", "value": 3}, {"name": "Kinder Blumen", "value": 5}, {"name": "Past Lives", "value": 9}, {"name": "Aprils Song", "value": 8}, {"name": "The Bend", "value": 5}, {"name": "Primitive", "value": 5}, {"name": "How Might I Live", "value": 4}, {"name": "Horizon", "value": 3}, {"name": "Navigator", "value": 6}, {"name": "Easy", "value": 17}, {"name": "Green Aisles", "value": 6}, {"name": "Its Real", "value": 7}, {"name": "Out Of Tune", "value": 5}, {"name": "Municipality", "value": 4}, {"name": "Wonder Years", "value": 3}, {"name": "Three Blocks", "value": 4}, {"name": "Younger Than Yesterday", "value": 2}, {"name": "All The Same", "value": 5}, {"name": "Fake Blues", "value": 2}, {"name": "Suburban Beverage", "value": 1}, {"name": "Beneath The Dunes", "value": 1}, {"name": "Basement", "value": 1}, {"name": "Suburban Dogs", "value": 1}, {"name": "Dumb Luck", "value": 1}, {"name": "Blue Lebaron", "value": 1}, {"name": "Snow Days", "value": 1}, {"name": "Saturday Morning", "value": 1}, {"name": "Black Lake", "value": 2}, {"name": "Drum", "value": 1}, {"name": "Paper Dolls", "value": 1}, {"name": "Exactly Nothing", "value": 1}, {"name": "Reservoir #3", "value": 1}, {"name": "Motorbikes", "value": 1}, {"name": "Pool Swimmers", "value": 1}, {"name": "Lets Rock the Beach", "value": 2}, {"name": "Paper Cup - Edit", "value": 1}, {"name": "You", "value": 2}, {"name": "Friday", "value": 1}, {"name": "Paper Cup", "value": 1}, {"name": "Gone", "value": 1}]}, {"name": "Laurel Halo", "children": [{"name": "Airsick", "value": 1}]}, {"name": "Dirty Projectors", "children": [{"name": "Death Spiral", "value": 1}, {"name": "Up In Hudson - edit", "value": 1}, {"name": "Keep Your Name", "value": 3}, {"name": "Break-Thru", "value": 1}, {"name": "Swing Lo Magellan", "value": 3}, {"name": "Up In Hudson", "value": 1}]}, {"name": "Angel Olsen", "children": [{"name": "Unfucktheworld", "value": 4}, {"name": "Never Be Mine", "value": 2}, {"name": "Heart Shaped Face", "value": 1}, {"name": "All Mirrors", "value": 1}, {"name": "Chance", "value": 1}]}, {"name": "Big Thief", "children": [{"name": "Paul", "value": 5}, {"name": "Shark Smile - Edit", "value": 2}, {"name": "Masterpiece - (solo)", "value": 1}, {"name": "Pretty Things", "value": 3}, {"name": "Objects", "value": 2}, {"name": "Shark Smile", "value": 2}, {"name": "Capacity", "value": 2}, {"name": "Watering", "value": 1}, {"name": "Coma", "value": 1}, {"name": "Masterpiece", "value": 2}, {"name": "UFOF", "value": 1}, {"name": "Cattails", "value": 1}]}, {"name": "Deerhunter", "children": [{"name": "Helicopter", "value": 4}, {"name": "Revival", "value": 2}, {"name": "He Would Have Laughed", "value": 6}]}, {"name": "Cass McCombs", "children": [{"name": "Opposite House", "value": 1}, {"name": "Laughter Is The Best Medicine", "value": 2}, {"name": "There Can Be Only One", "value": 2}, {"name": "Bum Bum Bum", "value": 2}, {"name": "Thats That", "value": 1}, {"name": "Dreams-Come-True-Girl", "value": 1}, {"name": "Sleeping Volcanoes", "value": 2}, {"name": "Minimum Wage", "value": 1}]}, {"name": "Waxahatchee", "children": [{"name": "Peace and Quiet", "value": 1}, {"name": "Fire", "value": 1}]}, {"name": "Clap Your Hands Say Yeah", "children": [{"name": "The Skin of My Yellow Country Teeth", "value": 5}, {"name": "The Pilot", "value": 2}]}, {"name": "Grandaddy", "children": [{"name": "The Boat is in the Barn", "value": 1}, {"name": "The Crystal Lake", "value": 2}]}, {"name": "Yo La Tengo", "children": [{"name": "Rickety", "value": 2}, {"name": "The Ballad of Red Buckets", "value": 2}, {"name": "Ill Be Around", "value": 7}, {"name": "You Are Here", "value": 4}, {"name": "Autumn Sweater", "value": 5}, {"name": "My Hearts Not In It", "value": 3}, {"name": "You Can Have It All", "value": 6}, {"name": "Green Arrow", "value": 2}, {"name": "Our Way to Fall", "value": 5}, {"name": "Nowhere Near", "value": 2}, {"name": "Cherry Chapstick", "value": 2}, {"name": "Double Dare", "value": 1}, {"name": "The Whole of the Law", "value": 1}, {"name": "Everyday", "value": 2}, {"name": "I Heard You Looking", "value": 1}, {"name": "Stockholm Syndrome", "value": 1}, {"name": "Today Is the Day", "value": 2}, {"name": "Leaving Home", "value": 1}, {"name": "Somebodys In Love", "value": 1}, {"name": "Tiny Birds", "value": 1}, {"name": "Lets Save Tony Orlandos House", "value": 1}, {"name": "From a Motel 6", "value": 1}, {"name": "Black Flowers", "value": 1}, {"name": "Here Comes My Baby", "value": 1}, {"name": "I Feel Like Going Home", "value": 1}, {"name": "Mr. Tough", "value": 1}, {"name": "Season of the Shark", "value": 2}, {"name": "Moby Octopad", "value": 1}, {"name": "Friday Im in Love", "value": 1}, {"name": "Saturday", "value": 1}, {"name": "Polynesia #1", "value": 2}, {"name": "Im So Lonesome I Could Cry", "value": 1}, {"name": "Tom Courtenay", "value": 1}, {"name": "Ashes", "value": 1}, {"name": "Big Day Coming", "value": 1}, {"name": "Here You Are", "value": 1}, {"name": "Automatic Doom", "value": 1}, {"name": "Sugarcube", "value": 1}, {"name": "Beach Party Tonight", "value": 1}]}, {"name": "Perfume Genius", "children": [{"name": "Valley", "value": 1}]}, {"name": "Ariel Pink", "children": [{"name": "Lipstick", "value": 2}, {"name": "Dayzed Inn Daydreams", "value": 1}, {"name": "Another Weekend", "value": 1}]}, {"name": "Parquet Courts", "children": [{"name": "Already Dead", "value": 2}, {"name": "Tenderness", "value": 2}, {"name": "Before the Water Gets Too High", "value": 2}, {"name": "Total Football", "value": 1}]}, {"name": "Pavement", "children": [{"name": "Harness Your Hopes - (B-side)", "value": 4}, {"name": "Father to a Sister of Thought", "value": 2}, {"name": "Range Life", "value": 10}, {"name": "Cut Your Hair", "value": 2}, {"name": "Gold Soundz", "value": 2}, {"name": "Gold Soundz (Remastered)", "value": 1}, {"name": "Starlings of the Slipstream", "value": 1}, {"name": "Stereo", "value": 2}, {"name": "Grave Architecture", "value": 1}, {"name": "Grounded", "value": 1}]}, {"name": "(Sandy) Alex G", "children": [{"name": "Sarah (Bonus Track)", "value": 3}, {"name": "Bobby", "value": 10}, {"name": "Hope", "value": 16}, {"name": "Walk Away", "value": 4}, {"name": "Poison Root", "value": 6}, {"name": "Proud", "value": 22}, {"name": "County", "value": 7}, {"name": "Witch", "value": 4}, {"name": "Horse", "value": 4}, {"name": "Brick", "value": 4}, {"name": "Big Fish", "value": 3}, {"name": "Southern Sky", "value": 8}, {"name": "Gretel", "value": 7}, {"name": "Sarah - Bonus Track", "value": 9}, {"name": "Brite Boy", "value": 2}, {"name": "Mary", "value": 3}, {"name": "Powerful Man", "value": 6}, {"name": "In My Arms", "value": 2}, {"name": "Taking", "value": 2}, {"name": "Sportstar", "value": 4}, {"name": "Judge", "value": 4}, {"name": "Rocket", "value": 2}, {"name": "Alina", "value": 2}, {"name": "Guilty", "value": 3}, {"name": "Harvey", "value": 1}, {"name": "Come Back", "value": 1}, {"name": "Forever", "value": 4}, {"name": "In Love", "value": 1}, {"name": "Kicker", "value": 2}, {"name": "After Ur Gone", "value": 1}, {"name": "16 Mirrors - Bonus Track", "value": 1}, {"name": "Sugar", "value": 1}, {"name": "SugarHouse - Live", "value": 1}, {"name": "Change", "value": 1}, {"name": "Salt", "value": 1}, {"name": "Bug", "value": 2}, {"name": "Ready", "value": 1}, {"name": "Mis", "value": 1}, {"name": "Waiting for You (Bonus Track)", "value": 1}]}, {"name": "Broken Social Scene", "children": [{"name": "Stay Happy", "value": 1}, {"name": "Anthems For A Seventeen Year-Old Girl", "value": 2}, {"name": "Cause = Time", "value": 1}, {"name": "Pacific Theme", "value": 1}, {"name": "Sweetest Kill", "value": 1}]}, {"name": "Amen Dunes", "children": [{"name": "Blue Rose", "value": 1}]}, {"name": "Galaxie 500", "children": [{"name": "Dont Let Our Youth Go to Waste", "value": 1}, {"name": "Tugboat", "value": 2}, {"name": "Blue Thunder", "value": 1}]}, {"name": "Jay Som", "children": [{"name": "Rush", "value": 3}, {"name": "Baybee", "value": 8}, {"name": "One More Time, Please", "value": 5}, {"name": "I Think Youre Alright", "value": 3}, {"name": "The Bus Song", "value": 4}, {"name": "Superbike", "value": 7}, {"name": "If You Want It", "value": 6}, {"name": "Peace Out", "value": 6}, {"name": "Devotion", "value": 6}, {"name": "Nighttime Drive", "value": 6}, {"name": "Tenderness", "value": 9}, {"name": "Anak Ko", "value": 6}, {"name": "Crown", "value": 6}, {"name": "Get Well", "value": 8}, {"name": "Lipstick Stains", "value": 3}, {"name": "Remain", "value": 2}, {"name": "1 Billion Dogs", "value": 2}, {"name": "(BedHead)", "value": 2}, {"name": "Take It", "value": 2}, {"name": "Everybody Works", "value": 2}, {"name": "For Light", "value": 2}, {"name": "Our Red Door", "value": 1}, {"name": "Next To Me", "value": 1}, {"name": "A Thousand Words", "value": 2}, {"name": "Pirouette", "value": 1}, {"name": "Cant Sleep", "value": 1}]}, {"name": "Fruit Bats", "children": [{"name": "My Sweet Midwest", "value": 2}, {"name": "The Rock Doc", "value": 2}, {"name": "Humbug Mountain Song", "value": 3}, {"name": "Flamingo", "value": 1}, {"name": "When U Love Somebody", "value": 2}, {"name": "The Bottom of It", "value": 1}]}, {"name": "Melodys Echo Chamber", "children": [{"name": "Breathe in, Breathe Out", "value": 1}, {"name": "I Follow You", "value": 1}, {"name": "Crystallized", "value": 1}, {"name": "You Wont Be Missing That Part of Me", "value": 1}, {"name": "Some Time Alone, Alone", "value": 1}, {"name": "Bisou Magique", "value": 1}, {"name": "Shirim", "value": 1}]}, {"name": "Drugdealer", "children": [{"name": "Suddenly", "value": 24}, {"name": "Sea of Nothing", "value": 13}, {"name": "The Real World", "value": 19}, {"name": "The End Of Comedy", "value": 18}, {"name": "Were You Saying Something?", "value": 26}, {"name": "Easy to Forget", "value": 22}, {"name": "Honey", "value": 21}, {"name": "Youve Got To Be Kidding", "value": 9}, {"name": "Lonely", "value": 13}, {"name": "Lost In My Dream", "value": 11}, {"name": "Fools", "value": 15}, {"name": "If You Dont Know Now, You Never Will", "value": 15}, {"name": "Wild Motion", "value": 8}, {"name": "London Nightmare", "value": 11}, {"name": "Ending On A Hi Note", "value": 8}, {"name": "My Life", "value": 7}, {"name": "Comedy Outro", "value": 7}, {"name": "Far Rockaway Theme", "value": 9}, {"name": "Its Only Raining Right Where Youre Standing", "value": 20}, {"name": "Theme For Alessandro", "value": 12}]}, {"name": "Cotton Jones", "children": [{"name": "I Am The Changer", "value": 12}, {"name": "Blood Red Sentimental Blues", "value": 5}, {"name": "Gotta Cheer Up", "value": 4}, {"name": "Down Beside Em", "value": 1}, {"name": "Lune Chatter", "value": 1}, {"name": "Egg On A Sea", "value": 1}, {"name": "Good In Every Word", "value": 1}, {"name": "Up A Tree (Went This Heart I Have)", "value": 1}, {"name": "Some Strange Rain", "value": 1}, {"name": "Gone The Bells", "value": 1}, {"name": "Photo Summerlude", "value": 1}, {"name": "By Morning Light", "value": 1}, {"name": "Cotton & Velvet", "value": 1}, {"name": "Little Ashtray In Sun", "value": 1}, {"name": "I Do What I Do: Exist & Pass", "value": 1}]}, {"name": "Spiritualized", "children": [{"name": "Ladies and Gentlemen We Are Floating in Space", "value": 8}, {"name": "Come Together", "value": 6}, {"name": "I Think Im In Love", "value": 1}, {"name": "All Of My Thoughts", "value": 1}, {"name": "Stay With Me", "value": 1}, {"name": "Electricity", "value": 2}, {"name": "Ladies And Gentlemen - A Cappella w/ Lead Vocal", "value": 1}, {"name": "No God Only Religion", "value": 3}, {"name": "All of My Thoughts", "value": 2}, {"name": "I Think Im in Love", "value": 2}, {"name": "Stay with Me", "value": 1}, {"name": "Home of the Brave", "value": 1}, {"name": "The Individual", "value": 1}, {"name": "Broken Heart", "value": 1}, {"name": "Cool Waves", "value": 1}, {"name": "Cop Shoot Cop...", "value": 1}]}, {"name": "Allah-Las", "children": [{"name": "Could Be You", "value": 11}, {"name": "Catamaran", "value": 11}, {"name": "Raspberry Jam", "value": 7}, {"name": "Ferus Gallery", "value": 9}, {"name": "Fish On The Sand", "value": 10}, {"name": "Busmans Holiday", "value": 8}, {"name": "Sacred Sands", "value": 4}, {"name": "Long Journey", "value": 3}, {"name": "No Voodoo", "value": 5}, {"name": "Dont You Forget It", "value": 5}, {"name": "Strange Heat", "value": 2}, {"name": "Satisfied", "value": 2}, {"name": "High & Dry", "value": 2}, {"name": "Sandy", "value": 3}, {"name": "Ela Navega", "value": 4}, {"name": "Tell Me (Whats on Your Mind)", "value": 1}, {"name": "Catalina", "value": 4}, {"name": "Mausoleum", "value": 2}, {"name": "Roadside Memorial", "value": 2}, {"name": "Autumn Dawn", "value": 2}, {"name": "Famous Phone Figure", "value": 3}, {"name": "200 South La Brea", "value": 2}, {"name": "In The Air", "value": 12}, {"name": "Star", "value": 12}, {"name": "Polar Onion", "value": 11}, {"name": "Holding Pattern", "value": 15}, {"name": "Keeping Dry", "value": 13}, {"name": "No Werewolf", "value": 3}, {"name": "Prazer Em Te Conhecer", "value": 11}, {"name": "Roco Ono", "value": 12}, {"name": "Royal Blues", "value": 10}, {"name": "Electricity", "value": 10}, {"name": "Light Yearly", "value": 10}, {"name": "On Our Way", "value": 7}, {"name": "Houston", "value": 6}, {"name": "Pleasure", "value": 5}, {"name": "Warmed Kippers", "value": 1}, {"name": "Terra Ignota", "value": 1}, {"name": "Place In The Sun", "value": 2}, {"name": "De Vida Voz", "value": 5}, {"name": "Had It All", "value": 5}, {"name": "Artifact", "value": 4}, {"name": "Recurring", "value": 2}, {"name": "Nothing to Hide", "value": 3}, {"name": "Buffalo Nickel", "value": 2}, {"name": "Follow You Down", "value": 2}, {"name": "501-415", "value": 2}, {"name": "Yemeni Jade", "value": 3}, {"name": "Worship the Sun", "value": 3}, {"name": "Better Than Mine", "value": 1}, {"name": "Every Girl", "value": 1}, {"name": "Tell Me (Whats On Your Mind)", "value": 3}, {"name": "Vis-A-Vis", "value": 2}, {"name": "Seven Point Five", "value": 2}, {"name": "Hard On Love", "value": 1}, {"name": "The Earth Wont Hold Me", "value": 2}, {"name": "Burning In Heaven", "value": 1}, {"name": "Brittany Glasz", "value": 1}, {"name": "Autumn Dawn - Alternative Take", "value": 1}, {"name": "Hereafter", "value": 1}, {"name": "Come On", "value": 2}, {"name": "I Cannot Lie", "value": 2}, {"name": "Lady Rachel", "value": 1}]}, {"name": "Sharon Van Etten", "children": [{"name": "Seventeen", "value": 5}, {"name": "Every Time the Sun Comes Up", "value": 2}, {"name": "The End of the World", "value": 2}, {"name": "Beaten Down", "value": 1}, {"name": "Our Love", "value": 2}, {"name": "You Shadow", "value": 2}, {"name": "Comeback Kid", "value": 1}, {"name": "We Are Fine", "value": 1}, {"name": "Jupiter 4", "value": 1}]}, {"name": "The Mountain Goats", "children": [{"name": "We Do It Different on the West Coast", "value": 1}, {"name": "This Year", "value": 2}, {"name": "No Children", "value": 2}, {"name": "Up the Wolves", "value": 1}, {"name": "Waylon Jennings Live!", "value": 1}]}, {"name": "Neutral Milk Hotel", "children": [{"name": "In the Aeroplane Over the Sea", "value": 20}, {"name": "King of Carrot Flowers Pt. 1", "value": 8}, {"name": "Holland, 1945", "value": 7}, {"name": "King of Carrot Flowers Pts. 2 & 3", "value": 5}, {"name": "Two-Headed Boy", "value": 8}, {"name": "Oh Comely", "value": 5}, {"name": "The Fool", "value": 4}, {"name": "Communist Daughter", "value": 4}, {"name": "Ghost", "value": 5}, {"name": "[untitled]", "value": 4}, {"name": "Two-Headed Boy Pt. 2", "value": 3}]}, {"name": "Karen Dalton", "children": [{"name": "Little Bit Of Rain", "value": 1}, {"name": "Something On Your Mind", "value": 1}]}, {"name": "Jeff Tweedy", "children": [{"name": "Some Birds", "value": 4}, {"name": "Laminated Cat", "value": 3}, {"name": "I Am Trying to Break Your Heart", "value": 3}, {"name": "I Know What Its Like", "value": 3}, {"name": "Bombs Above", "value": 2}, {"name": "Dont Forget", "value": 1}, {"name": "Via Chicago", "value": 2}, {"name": "Having Been Is No Way To Be", "value": 1}]}, {"name": "Atlas Sound", "children": [{"name": "Walkabout (W/ Noah Lennox)", "value": 1}]}, {"name": "King Tuff", "children": [{"name": "Sun Medallion", "value": 1}]}, {"name": "Stereolab", "children": [{"name": "Brakhage", "value": 1}, {"name": "Lo Boob Oscillator", "value": 2}]}, {"name": "Wand", "children": [{"name": "Melted Rope", "value": 4}, {"name": "Flying Golem", "value": 2}, {"name": "Scarecrow", "value": 1}]}, {"name": "Ty Segall", "children": [{"name": "My Ladys On Fire", "value": 13}, {"name": "Every 1s a Winner", "value": 6}, {"name": "The Singer", "value": 2}, {"name": "Finger", "value": 1}, {"name": "Girlfriend", "value": 1}, {"name": "Slowboat", "value": 1}, {"name": "Fanny Dog", "value": 2}, {"name": "Rain", "value": 1}, {"name": "Despoiler of Cadaver", "value": 2}, {"name": "Taste", "value": 1}, {"name": "Whatever", "value": 1}, {"name": "Whos Producing You?", "value": 1}]}, {"name": "Stephen Malkmus & The Jicks", "children": [{"name": "Out of Reaches", "value": 1}, {"name": "Gardenia", "value": 1}]}, {"name": "Richard Swift", "children": [{"name": "Lady Luck", "value": 2}]}, {"name": "Sonny & The Sunsets", "children": [{"name": "Too Young to Burn", "value": 1}, {"name": "Pretend You Love Me", "value": 1}]}, {"name": "Sam Evian", "children": [{"name": "IDGAF", "value": 4}, {"name": "Next to You ", "value": 3}, {"name": "Dark Love", "value": 6}, {"name": "Right Down the Line", "value": 2}, {"name": "Sleep Easy", "value": 4}, {"name": "Cactus", "value": 4}, {"name": "Big Car", "value": 3}, {"name": "Carolina", "value": 2}, {"name": "I Need a Man", "value": 2}, {"name": "Summer Running", "value": 2}, {"name": "Golden Skull", "value": 1}, {"name": "Tear", "value": 1}, {"name": "Where Did You Go?", "value": 2}, {"name": "Health Machine", "value": 2}, {"name": "Anybody", "value": 2}, {"name": "Apple", "value": 2}, {"name": "Country", "value": 2}, {"name": "Next to You", "value": 1}, {"name": "Summer Day", "value": 1}, {"name": "Now I Feel It", "value": 1}, {"name": "You, Forever", "value": 1}, {"name": "Katies Rhodes", "value": 1}, {"name": "Cherry Tree", "value": 1}]}, {"name": "Girls", "children": [{"name": "Oh So Protective One", "value": 1}]}, {"name": "Weyes Blood", "children": [{"name": "Movies", "value": 1}, {"name": "Seven Words", "value": 1}]}, {"name": "Andrew Bird", "children": [{"name": "/=/", "value": 2}, {"name": "Masterfade", "value": 1}, {"name": "The Naming of Things", "value": 1}, {"name": "Tables and Chairs", "value": 1}, {"name": "Roma Fade", "value": 1}, {"name": "Truth Lies Low", "value": 1}]}, {"name": "of Montreal", "children": [{"name": "Lysergic Bliss", "value": 1}]}, {"name": "Silver Jews", "children": [{"name": "People", "value": 1}, {"name": "Dallas", "value": 1}, {"name": "The Wild Kindness", "value": 2}, {"name": "Suffering Jukebox", "value": 1}]}, {"name": "Microphones", "children": [{"name": "I Want Wind to Blow", "value": 2}, {"name": "The Moon", "value": 1}]}, {"name": "Built To Spill", "children": [{"name": "Carry the Zero", "value": 1}]}, {"name": "Karl Blau", "children": [{"name": "Before Telling Dragons", "value": 1}]}, {"name": "WHY?", "children": [{"name": "Stained Glass Slipper", "value": 1}]}, {"name": "Michael Nau", "children": [{"name": "No Quit", "value": 1}]}, {"name": "Hailu Mergia", "children": [{"name": "Lala Belu", "value": 1}]}, {"name": "Vetiver", "children": [{"name": "Strictly Rule", "value": 1}]}, {"name": "The Brian Jonestown Massacre", "children": [{"name": "Anemone", "value": 1}]}, {"name": "The Magnetic Fields", "children": [{"name": "Strange Powers", "value": 2}]}, {"name": "Songs: Ohia", "children": [{"name": "Farewell Transmission", "value": 1}]}, {"name": "Wolf Parade", "children": [{"name": "Fine Young Cannibals", "value": 1}]}, {"name": "Hamilton Leithauser", "children": [{"name": "The Silent Orchestra", "value": 1}]}, {"name": "Andy Shauf", "children": [{"name": "Neon Skyline", "value": 3}, {"name": "The Magician", "value": 3}, {"name": "Where Are You Judy", "value": 1}, {"name": "Clove Cigarette", "value": 1}, {"name": "Thirteen Hours", "value": 1}, {"name": "Things I Do", "value": 1}, {"name": "Living Room", "value": 1}, {"name": "Youre Out Wasting", "value": 1}]}, {"name": "Mikal Cronin", "children": [{"name": "Weight", "value": 1}]}, {"name": "Sparklehorse", "children": [{"name": "Its A Wonderful Life", "value": 1}]}, {"name": "Oneohtrix Point Never", "children": [{"name": "Babylon", "value": 5}]}, {"name": "Cate Le Bon", "children": [{"name": "Home To You", "value": 2}, {"name": "Are You With Me Now?", "value": 1}]}, {"name": "Omni", "children": [{"name": "Wire", "value": 2}]}, {"name": "Adrianne Lenker", "children": [{"name": "Indiana", "value": 1}]}, {"name": "Purple Mountains", "children": [{"name": "Snow is Falling in Manhattan", "value": 1}]}, {"name": "Black Lips", "children": [{"name": "Modern Art", "value": 1}, {"name": "Spideys Curse", "value": 1}]}, {"name": "Stephen Malkmus and The Jicks", "children": [{"name": "Lariat", "value": 2}]}, {"name": "Man Man", "children": [{"name": "Head On (Hold On To Your Heart)", "value": 1}]}, {"name": "The Cleaners From Venus", "children": [{"name": "Only a Shadow", "value": 1}]}, {"name": "The Sea and Cake", "children": [{"name": "Sound & Vision", "value": 1}, {"name": "Jacking the Ball", "value": 1}, {"name": "Mr. F", "value": 1}]}, {"name": "The Walkmen", "children": [{"name": "Another One Goes By", "value": 1}]}, {"name": "Kikagaku Moyo", "children": [{"name": "Smoke and Mirrors", "value": 1}]}, {"name": "Porridge Radio", "children": [{"name": "Sweet", "value": 1}, {"name": "Lilac", "value": 1}]}, {"name": "Natural Child", "children": [{"name": "Out in the Country", "value": 4}, {"name": "Bennys Here", "value": 3}, {"name": "Sure Is Nice", "value": 3}, {"name": "DTV", "value": 2}, {"name": "NSA Blues", "value": 1}, {"name": "Self Centered Blues", "value": 1}, {"name": "Its A Shame My Store Isnt Open", "value": 2}]}, {"name": "Protomartyr", "children": [{"name": "Processed By The Boys", "value": 1}]}, {"name": "Yves Tumor", "children": [{"name": "Kerosene!", "value": 1}]}]}