{"name": "songData", "children": [{"name": "Jamie xx", "children": [{"name": "I Know Theres Gonna Be (Good Times)", "value": 10}, {"name": "Gosh", "value": 3}, {"name": "Obvs", "value": 2}, {"name": "Loud Places ", "value": 5}, {"name": "SeeSaw ", "value": 1}, {"name": "Far Nearer", "value": 1}, {"name": "The Rest Is Noise", "value": 1}, {"name": "Girl", "value": 2}]}, {"name": "Moon Taxi", "children": [{"name": "Morocco", "value": 9}, {"name": "River Water", "value": 16}, {"name": "Mercury", "value": 1}, {"name": "Running Wild", "value": 13}, {"name": "Beaches", "value": 3}, {"name": "Suspicious", "value": 3}, {"name": "Struck Me Down", "value": 2}, {"name": "The New Black", "value": 2}, {"name": "Change", "value": 1}, {"name": "Red Hot Lights", "value": 1}, {"name": "Cabaret", "value": 2}, {"name": "Make Your Mind Up", "value": 1}, {"name": "Year Zero", "value": 12}, {"name": "All Day All Night", "value": 1}, {"name": "Ready To Go", "value": 1}, {"name": "Domino", "value": 1}, {"name": "Always", "value": 1}, {"name": "Savannah", "value": 1}, {"name": "Rooftops", "value": 1}, {"name": "Run Right Back", "value": 7}, {"name": "Whos To Say?", "value": 1}, {"name": "Young Journey", "value": 5}, {"name": "Let The Record Play", "value": 1}, {"name": "Not Too Late", "value": 1}, {"name": "Good As Gold", "value": 1}, {"name": "Two High", "value": 1}, {"name": "No More Worry", "value": 1}, {"name": "Moving To The City", "value": 1}, {"name": "Nothing Can Keep Us Apart", "value": 1}, {"name": "Juniper", "value": 2}]}, {"name": "SBTRKT", "children": [{"name": "Spaced Out", "value": 1}, {"name": "Wildfire", "value": 2}]}, {"name": "Destroyer", "children": [{"name": "Blue Eyes", "value": 1}, {"name": "Chinatown", "value": 1}, {"name": "Painter in Your Pocket", "value": 5}, {"name": "Rubies", "value": 2}, {"name": "Its Gonna Take an Airplane", "value": 1}, {"name": "Crimson Tide", "value": 1}]}, {"name": "Flying Lotus", "children": [{"name": "Never Catch Me", "value": 3}]}, {"name": "James Blake", "children": [{"name": "I Need A Forest Fire", "value": 4}, {"name": "Modern Soul", "value": 1}, {"name": "Cant Believe The Way We Flow", "value": 1}, {"name": "Mile High ", "value": 1}]}, {"name": "Bibio", "children": [{"name": "Town & Country", "value": 4}, {"name": "Im Rewinding It...", "value": 1}, {"name": "jealous of roses", "value": 1}, {"name": "Petals", "value": 1}, {"name": "Old Graffiti", "value": 1}, {"name": "\u00c0 tout \u00e0 lheure", "value": 1}, {"name": "Lovers Carvings - WXAXRXP Session", "value": 1}]}, {"name": "Big Wild", "children": [{"name": "Aftergold ", "value": 1}, {"name": "Aftergold", "value": 2}, {"name": "6s to 9s ", "value": 1}, {"name": "When I Get There", "value": 1}, {"name": "Show Me", "value": 1}, {"name": "Joypunks", "value": 1}]}, {"name": "Lapalux", "children": [{"name": "We Lost", "value": 1}]}, {"name": "The Avalanches", "children": [{"name": "Since I Left You", "value": 1}, {"name": "Because I\u2019m Me", "value": 1}, {"name": "Subways", "value": 2}, {"name": "We Will Always Love You ", "value": 1}]}, {"name": "Sylvan Esso", "children": [{"name": "Wolf", "value": 3}, {"name": "Funeral Singers", "value": 2}]}, {"name": "Beach House", "children": [{"name": "PPP", "value": 21}, {"name": "Sparks", "value": 28}, {"name": "Used to Be", "value": 4}, {"name": "Real Love", "value": 3}, {"name": "All Your Yeahs", "value": 4}, {"name": "Wedding Bell", "value": 4}, {"name": "Better Times", "value": 4}, {"name": "Days of Candy", "value": 20}, {"name": "Lover of Mine", "value": 4}, {"name": "Space Song", "value": 47}, {"name": "Other People", "value": 5}, {"name": "10:37", "value": 20}, {"name": "Lazuli", "value": 14}, {"name": "Levitation", "value": 35}, {"name": "Elegy to the Void", "value": 4}, {"name": "Somewhere Tonight", "value": 6}, {"name": "Wild", "value": 6}, {"name": "Bluebird", "value": 21}, {"name": "Beyond Love", "value": 20}, {"name": "Wildflower", "value": 19}, {"name": "Shes So Lovely", "value": 3}, {"name": "Rough Song", "value": 2}, {"name": "One Thing", "value": 3}, {"name": "The Hours", "value": 3}, {"name": "Irene", "value": 3}, {"name": "On the Sea", "value": 3}, {"name": "New Year", "value": 3}, {"name": "Myth", "value": 17}, {"name": "Troublemaker", "value": 1}, {"name": "Wishes", "value": 2}, {"name": "Zebra", "value": 7}, {"name": "10 Mile Stereo", "value": 3}, {"name": "Silver Soul", "value": 6}, {"name": "Take Care", "value": 10}, {"name": "You Came To Me", "value": 4}, {"name": "Saltwater", "value": 5}, {"name": "Turtle Island", "value": 3}, {"name": "Auburn And Ivory", "value": 1}, {"name": "Walk in the Park", "value": 5}, {"name": "Norway", "value": 2}, {"name": "Childhood", "value": 2}, {"name": "Tokyo Witch", "value": 2}, {"name": "The Traveller", "value": 4}, {"name": "Holy Dances", "value": 3}, {"name": "Gila", "value": 5}, {"name": "The Arrangement", "value": 3}, {"name": "Wherever You Go", "value": 1}, {"name": "Chariot", "value": 6}, {"name": "Saturn Song", "value": 3}, {"name": "10 Mile Stereo - Cough Syrup Remix", "value": 1}, {"name": "Used to Be - 2008 Single Version", "value": 3}, {"name": "Baseball Diamond", "value": 4}, {"name": "I Do Not Care for the Winter Sun", "value": 3}, {"name": "Play the Game", "value": 3}, {"name": "Baby", "value": 6}, {"name": "White Moon - iTunes Session Remix", "value": 5}, {"name": "Equal Mind", "value": 7}, {"name": "Rain in Numbers", "value": 2}, {"name": "Norway - iTunes Session Remix", "value": 3}, {"name": "Majorette", "value": 4}, {"name": "Common Girl", "value": 2}, {"name": "Heart of Chambers", "value": 4}, {"name": "Master of None", "value": 20}, {"name": "Pay No Mind", "value": 24}, {"name": "Dark Spring", "value": 22}, {"name": "LInconnue", "value": 18}, {"name": "Drunk In LA", "value": 26}, {"name": "Last Ride", "value": 14}, {"name": "Lose Your Smile", "value": 33}, {"name": "Black Car", "value": 22}, {"name": "Girl Of The Year", "value": 14}, {"name": "Lemon Glow", "value": 24}, {"name": "Woo", "value": 18}, {"name": "Dive", "value": 37}, {"name": "All The Years", "value": 2}, {"name": "Some Things Last a Long Time", "value": 2}, {"name": "Astronaut", "value": 2}, {"name": "D.A.R.L.I.N.G.", "value": 2}, {"name": "Home Again", "value": 3}, {"name": "Apple Orchard", "value": 1}, {"name": "Auburn and Ivory", "value": 2}]}, {"name": "MGMT", "children": [{"name": "Congratulations", "value": 10}, {"name": "Its Working", "value": 9}, {"name": "Song for Dan Treacy", "value": 10}, {"name": "Someones Missing", "value": 7}, {"name": "Flash Delirium", "value": 9}, {"name": "I Found a Whistle", "value": 9}, {"name": "Siberian Breaks", "value": 8}, {"name": "Brian Eno", "value": 8}, {"name": "Lady Dadas Nightmare", "value": 4}, {"name": "The Youth", "value": 15}, {"name": "Weekend Wars", "value": 7}, {"name": "Time to Pretend", "value": 5}, {"name": "Alien Days", "value": 1}, {"name": "Electric Feel", "value": 7}, {"name": "Kids", "value": 8}, {"name": "4th Dimensional Transition", "value": 5}, {"name": "Pieces of What", "value": 6}, {"name": "Of Moons, Birds & Monsters", "value": 4}, {"name": "The Handshake", "value": 5}, {"name": "Future Reflections", "value": 5}, {"name": "Stop & Smell the Roses", "value": 1}, {"name": "Mound of Clay", "value": 1}, {"name": "Song for Wilde", "value": 1}, {"name": "All We Ever Wanted Was Everything", "value": 2}, {"name": "A Good Sadness", "value": 1}, {"name": "Introspection", "value": 1}, {"name": "Mystery Disease", "value": 2}, {"name": "Cool Song No. 2", "value": 2}, {"name": "I Love You Too, Death", "value": 1}, {"name": "Plenty Of Girls In The Sea", "value": 1}, {"name": "Your Life Is a Lie", "value": 1}, {"name": "An Orphan Of Fortune", "value": 1}, {"name": "Astro-Mancy", "value": 1}, {"name": "Siberian Breaks - Ed Banger All-Stars Remix", "value": 1}, {"name": "Congratulations - Erol Alkan Remix", "value": 1}, {"name": "Hand It Over", "value": 1}, {"name": "One Thing Left to Try", "value": 1}, {"name": "Indie Rokkers", "value": 2}, {"name": "Me and Michael", "value": 1}, {"name": "When You Die", "value": 1}, {"name": "In The Afternoon", "value": 2}]}, {"name": "Monster Rally", "children": [{"name": "Burning Citrus", "value": 1}, {"name": "Lovely You", "value": 1}]}, {"name": "Foxygen", "children": [{"name": "Shuggie", "value": 34}, {"name": "On Blue Mountain", "value": 18}, {"name": "San Francisco", "value": 29}, {"name": "Follow the Leader", "value": 15}, {"name": "Avalon", "value": 7}, {"name": "How Can You Really", "value": 1}, {"name": "No Destruction", "value": 4}, {"name": "Cosmic Vibrations", "value": 3}, {"name": "In the Darkness", "value": 19}, {"name": "Bowling Trophies", "value": 7}, {"name": "Oh Yeah", "value": 7}, {"name": "Wallys Farm", "value": 2}, {"name": "Star Power I: Overture", "value": 1}, {"name": "Make It Known", "value": 2}, {"name": "The Game", "value": 1}, {"name": "Oh No", "value": 6}, {"name": "Cant Contextualize My Mind", "value": 1}, {"name": "Take The Kids Off Broadway", "value": 3}, {"name": "America", "value": 2}, {"name": "Abandon My Toys", "value": 1}, {"name": "Teenage Alien Blues", "value": 1}, {"name": "Waitin 4 U", "value": 1}, {"name": "Middle School Dance (Song For Richard Swift)", "value": 1}, {"name": "Why Did I Get Married?", "value": 1}, {"name": "We Are the 21st Century Ambassadors of Peace & Magic", "value": 4}, {"name": "Mrs. Adams", "value": 2}, {"name": "On Lankershim", "value": 2}, {"name": "Star Power Airlines", "value": 1}, {"name": "Wheres the Money?", "value": 1}, {"name": "You & I", "value": 1}, {"name": "Livin a Lie", "value": 2}, {"name": "Face The Facts", "value": 1}, {"name": "Work", "value": 2}, {"name": "Mona", "value": 1}, {"name": "Seeing Other People", "value": 2}, {"name": "Face the Facts", "value": 2}, {"name": "The Thing Is", "value": 1}, {"name": "News", "value": 1}, {"name": "Flag at Half-Mast", "value": 1}, {"name": "The Conclusion", "value": 1}]}, {"name": "Animal Collective", "children": [{"name": "Mountain Game", "value": 1}, {"name": "What Would I Want? Sky", "value": 3}, {"name": "My Girls", "value": 3}, {"name": "Man Of Oil", "value": 1}, {"name": "Summertime Clothes", "value": 1}]}, {"name": "Generationals", "children": [{"name": "When They Fight, They Fight", "value": 15}, {"name": "Put a Light On", "value": 18}, {"name": "TenTwentyTen", "value": 3}, {"name": "Catahoula Man", "value": 5}, {"name": "Would You Want Me", "value": 1}, {"name": "It May Get Bad When Youre Lonely and Cold", "value": 1}]}, {"name": "Tycho", "children": [{"name": "Spectre - Bibio Remix", "value": 1}, {"name": "Weather", "value": 1}]}, {"name": "Jai Paul", "children": [{"name": "jasmine (demo)", "value": 2}, {"name": "He", "value": 1}]}, {"name": "Ella Vos", "children": [{"name": "White Noise (R3hab Remix)", "value": 1}]}, {"name": "Future Islands", "children": [{"name": "Ran", "value": 1}, {"name": "North Star", "value": 1}, {"name": "Seasons (Waiting On You)", "value": 4}, {"name": "Little Dreamer", "value": 1}, {"name": "Ancient Water", "value": 1}]}, {"name": "LCD Soundsystem", "children": [{"name": "Daft Punk Is Playing at My House", "value": 2}, {"name": "Tribulations", "value": 3}, {"name": "Never as Tired as When Im Waking Up", "value": 14}, {"name": "Beat Connection", "value": 2}, {"name": "Yr Citys a Sucker", "value": 2}, {"name": "Losing My Edge", "value": 2}, {"name": "Too Much Love", "value": 2}, {"name": "call the police", "value": 8}, {"name": "american dream", "value": 7}, {"name": "Dance Yrself Clean", "value": 12}, {"name": "All My Friends", "value": 14}, {"name": "Someone Great", "value": 11}, {"name": "Drunk Girls", "value": 5}, {"name": "All I Want", "value": 6}, {"name": "You Wanted A Hit", "value": 5}, {"name": "Home", "value": 6}, {"name": "Somebodys Calling Me", "value": 5}, {"name": "Pow Pow", "value": 5}, {"name": "45:33 Intro - live at madison square garden", "value": 2}, {"name": "us v them - live at madison square garden", "value": 1}, {"name": "Get Innocuous!", "value": 4}, {"name": "Time to Get Away", "value": 3}, {"name": "North American Scum", "value": 3}, {"name": "Us V Them", "value": 5}, {"name": "Watch the Tapes", "value": 5}, {"name": "Sound of Silver", "value": 5}, {"name": "New York, I Love You but Youre Bringing Me Down", "value": 16}, {"name": "One Touch", "value": 3}, {"name": "I Can Change", "value": 11}, {"name": "Movement", "value": 1}, {"name": "On Repeat", "value": 2}, {"name": "Thrills", "value": 2}, {"name": "Disco Infiltrator", "value": 2}, {"name": "Great Release", "value": 1}, {"name": "oh baby", "value": 4}, {"name": "other voices", "value": 2}, {"name": "i used to", "value": 2}, {"name": "change yr mind", "value": 2}, {"name": "how do you sleep?", "value": 5}, {"name": "tonite", "value": 2}, {"name": "emotional haircut", "value": 1}, {"name": "black screen", "value": 1}, {"name": "pulse (v.1)", "value": 1}, {"name": "Christmas Will Break Your Heart", "value": 1}]}, {"name": "Real Estate", "children": [{"name": "Darling", "value": 35}, {"name": "Talking Backwards", "value": 30}, {"name": "Had To Hear", "value": 26}, {"name": "Stained Glass", "value": 8}, {"name": "Serve The Song", "value": 7}, {"name": "Beach Comber", "value": 11}, {"name": "Saturday", "value": 10}, {"name": "Crime", "value": 9}, {"name": "After The Moon", "value": 4}, {"name": "Two Arrows", "value": 4}, {"name": "White Light", "value": 4}, {"name": "Holding Pattern", "value": 4}, {"name": "Time", "value": 4}, {"name": "Diamond Eyes", "value": 5}, {"name": "Same Sun", "value": 3}, {"name": "Kinder Blumen", "value": 5}, {"name": "Past Lives", "value": 9}, {"name": "Aprils Song", "value": 8}, {"name": "The Bend", "value": 5}, {"name": "Primitive", "value": 5}, {"name": "How Might I Live", "value": 4}, {"name": "Horizon", "value": 3}, {"name": "Navigator", "value": 6}, {"name": "Easy", "value": 17}, {"name": "Green Aisles", "value": 6}, {"name": "Its Real", "value": 7}, {"name": "Out Of Tune", "value": 5}, {"name": "Municipality", "value": 4}, {"name": "Wonder Years", "value": 3}, {"name": "Three Blocks", "value": 4}, {"name": "Younger Than Yesterday", "value": 2}, {"name": "All The Same", "value": 5}, {"name": "Fake Blues", "value": 2}, {"name": "Suburban Beverage", "value": 1}, {"name": "Beneath The Dunes", "value": 1}, {"name": "Basement", "value": 1}, {"name": "Suburban Dogs", "value": 1}, {"name": "Dumb Luck", "value": 1}, {"name": "Blue Lebaron", "value": 1}, {"name": "Snow Days", "value": 1}, {"name": "Saturday Morning", "value": 1}, {"name": "Black Lake", "value": 2}, {"name": "Drum", "value": 1}, {"name": "Paper Dolls", "value": 1}, {"name": "Exactly Nothing", "value": 1}, {"name": "Reservoir #3", "value": 1}, {"name": "Motorbikes", "value": 1}, {"name": "Pool Swimmers", "value": 1}, {"name": "Lets Rock the Beach", "value": 2}, {"name": "Paper Cup - Edit", "value": 1}, {"name": "You", "value": 2}, {"name": "Friday", "value": 1}, {"name": "Paper Cup", "value": 1}, {"name": "Gone", "value": 1}]}, {"name": "A R I Z O N A", "children": [{"name": "Oceans Away", "value": 1}]}, {"name": "Phoenix", "children": [{"name": "J-Boy", "value": 1}]}, {"name": "Arcade Fire", "children": [{"name": "Everything Now", "value": 1}, {"name": "Neighborhood #1 (Tunnels)", "value": 23}, {"name": "Neighborhood #2 (Laika)", "value": 12}, {"name": "Une Annee Sans Lumiere", "value": 10}, {"name": "Neighborhood #3 (Power Out)", "value": 10}, {"name": "Neighborhood #4 (7 Kettles)", "value": 12}, {"name": "Crown of Love", "value": 15}, {"name": "Wake Up", "value": 15}, {"name": "Haiti", "value": 9}, {"name": "Rebellion (Lies)", "value": 9}, {"name": "In the Backseat", "value": 6}, {"name": "Ready to Start", "value": 15}, {"name": "Modern Man", "value": 10}, {"name": "Rococo", "value": 6}, {"name": "Empty Room", "value": 6}, {"name": "City With No Children", "value": 7}, {"name": "Half Light I", "value": 7}, {"name": "Half Light II (No Celebration)", "value": 5}, {"name": "Suburban War", "value": 11}, {"name": "Month of May", "value": 6}, {"name": "Wasted Hours", "value": 5}, {"name": "Deep Blue", "value": 4}, {"name": "We Used to Wait", "value": 5}, {"name": "Sprawl I (Flatland)", "value": 4}, {"name": "Sprawl II (Mountains Beyond Mountains)", "value": 4}, {"name": "The Suburbs", "value": 22}, {"name": "The Suburbs (continued)", "value": 2}, {"name": "We Exist", "value": 1}, {"name": "Put Your Money on Me", "value": 1}, {"name": "Keep the Car Running", "value": 1}, {"name": "Signs of Life", "value": 1}, {"name": "Good God Damn", "value": 1}]}, {"name": "Dirty Projectors", "children": [{"name": "Death Spiral", "value": 1}, {"name": "Up In Hudson - edit", "value": 1}, {"name": "Keep Your Name", "value": 3}, {"name": "Break-Thru", "value": 1}, {"name": "Swing Lo Magellan", "value": 3}, {"name": "Up In Hudson", "value": 1}]}, {"name": "Unknown Mortal Orchestra", "children": [{"name": "So Good at Being in Trouble", "value": 1}, {"name": "Hunnybee", "value": 23}, {"name": "A God Called Hubris", "value": 7}, {"name": "This Doomsday", "value": 8}, {"name": "Chronos Feasts on His Children", "value": 8}, {"name": "Major League Chemicals", "value": 8}, {"name": "Multi-Love", "value": 12}, {"name": "So Good At Being in Trouble", "value": 28}, {"name": "Necessary Evil", "value": 13}, {"name": "Everyone Acts Crazy Nowadays", "value": 9}, {"name": "Ffunny Ffriends", "value": 2}, {"name": "Swim and Sleep (Like a Shark)", "value": 9}, {"name": "Hanoi 6", "value": 2}, {"name": "Ministry of Alienation", "value": 14}, {"name": "From the Sun", "value": 9}, {"name": "Not in Love We\u2019re Just High", "value": 7}, {"name": "American Guilt", "value": 6}, {"name": "The Internet of Love (That Way)", "value": 6}, {"name": "How Many Zeros", "value": 7}, {"name": "If You\u2019re Going to Break Yourself", "value": 7}, {"name": "Dawn", "value": 9}, {"name": "One at a Time", "value": 7}, {"name": "The Opposite of Afternoon", "value": 6}, {"name": "Monki", "value": 7}, {"name": "Faded in the Morning", "value": 7}, {"name": "No Need for a Leader", "value": 6}, {"name": "Secret Xtians", "value": 4}, {"name": "Like Acid Rain", "value": 3}, {"name": "Ur Life One Night", "value": 3}, {"name": "Can\u2019t Keep Checking My Phone", "value": 3}, {"name": "Extreme Wealth and Casual Cruelty", "value": 3}, {"name": "The World Is Crowded", "value": 7}, {"name": "Stage or Screen", "value": 3}, {"name": "Puzzles", "value": 3}, {"name": "Swing Lo Magellan - Acoustic Version", "value": 1}, {"name": "Hanoi 1", "value": 1}, {"name": "SB-06", "value": 1}]}, {"name": "Andrew McMahon in the Wilderness", "children": [{"name": "Cecilia And The Satellite", "value": 1}]}, {"name": "Toro Y Moi", "children": [{"name": "Lilly", "value": 2}, {"name": "Omaha", "value": 19}, {"name": "New Beat", "value": 3}, {"name": "Mirage", "value": 1}, {"name": "Girl Like You", "value": 8}, {"name": "So Many Details", "value": 3}, {"name": "Ordinary Pleasure", "value": 5}, {"name": "Talamak", "value": 1}, {"name": "Rose Quartz", "value": 1}, {"name": "Freelance", "value": 1}, {"name": "Empty Nesters", "value": 1}, {"name": "Buffalo", "value": 1}, {"name": "What You Want", "value": 1}, {"name": "You Hid", "value": 1}, {"name": "Divina", "value": 1}, {"name": "Still Sound", "value": 1}, {"name": "drip bounce _ 7_24_18", "value": 1}, {"name": "4-26-18_tonys_drewbanga_hifi", "value": 1}, {"name": "Monte Carlo ", "value": 2}, {"name": "Say That", "value": 1}, {"name": "Yeah Right", "value": 1}, {"name": "castaway_tron_hifi_v2 ", "value": 1}, {"name": "Touch", "value": 1}, {"name": "Laws of the Universe", "value": 1}]}, {"name": "Beach Fossils", "children": [{"name": "Sleep Apnea", "value": 7}, {"name": "Social Jetlag", "value": 3}, {"name": "Saint Ivy", "value": 1}, {"name": "This Year", "value": 2}, {"name": "What a Pleasure", "value": 2}, {"name": "Down the Line", "value": 4}, {"name": "May 1st", "value": 2}, {"name": "Sugar", "value": 1}]}, {"name": "Washed Out", "children": [{"name": "It All Feels Right", "value": 2}, {"name": "Feel It All Around", "value": 3}, {"name": "Face Up", "value": 2}, {"name": "Hard To Say Goodbye", "value": 4}]}, {"name": "Day Wave", "children": [{"name": "Wasting Time", "value": 1}, {"name": "Drag", "value": 1}, {"name": "Gone", "value": 2}, {"name": "Something Here", "value": 1}]}, {"name": "Sir Sly", "children": [{"name": "2am", "value": 1}, {"name": "Ghost", "value": 1}, {"name": "&Run", "value": 2}]}, {"name": "TV Girl", "children": [{"name": "Lovers Rock", "value": 11}, {"name": "Birds Dont Sing", "value": 23}, {"name": "Pantyhose", "value": 11}, {"name": "Louise", "value": 9}, {"name": "Pretty Boy", "value": 8}, {"name": "7 Days Til Sunday", "value": 22}, {"name": "Blue Hair", "value": 10}, {"name": "Lonely Girls", "value": 8}, {"name": "Drift Down", "value": 6}, {"name": "Cynical One", "value": 7}, {"name": "King of Echo Park", "value": 19}, {"name": "Legendary Lovers", "value": 8}, {"name": "Every Stupid Actress", "value": 20}, {"name": "Death of a Party Girl", "value": 4}, {"name": "Hate Yourself", "value": 19}, {"name": "The Getaway", "value": 4}, {"name": "Talk to Strangers", "value": 6}, {"name": "The Blonde", "value": 4}, {"name": "Daughter of a Cop", "value": 3}, {"name": "Her and Her Friend", "value": 4}, {"name": "Anjela", "value": 5}, {"name": "Come When You Call", "value": 2}, {"name": "Taking Whats Not Yours", "value": 10}, {"name": "Song About Me", "value": 4}, {"name": "Cigarettes out the Window", "value": 7}, {"name": "Till You Tell Me to Leave", "value": 4}, {"name": "Not Allowed", "value": 2}, {"name": "(Do The) Act Like You Never Met Me", "value": 2}, {"name": "Safeword", "value": 2}, {"name": "For You", "value": 2}, {"name": "Loving Machine", "value": 15}, {"name": "Heaven Is a Bedroom", "value": 3}, {"name": "Melanie", "value": 1}]}, {"name": "Mating Ritual", "children": [{"name": "Cold ", "value": 1}]}, {"name": "Portugal. The Man", "children": [{"name": "Feel It Still", "value": 2}, {"name": "The Sun", "value": 1}, {"name": "Feel It Still - Medasin Remix", "value": 1}]}, {"name": "Electric Guest", "children": [{"name": "Oh Devil", "value": 10}, {"name": "Oh Devil - Radio Version", "value": 3}, {"name": "Dollar", "value": 5}, {"name": "This Head I Hold", "value": 4}, {"name": "Dear To Me", "value": 7}, {"name": "More", "value": 4}, {"name": "American Daydream", "value": 3}, {"name": "Back For Me", "value": 3}, {"name": "Play With Me", "value": 2}, {"name": "Waves", "value": 4}, {"name": "Back On Me", "value": 3}, {"name": "Glorious Warrior", "value": 2}, {"name": "Freestyle", "value": 2}, {"name": "Awake", "value": 2}, {"name": "Holiday", "value": 2}, {"name": "Bound To Lose", "value": 2}, {"name": "I Got The Money", "value": 2}, {"name": "Basic", "value": 1}]}, {"name": "Neon Indian", "children": [{"name": "The Glitzy Hive", "value": 2}, {"name": "Annie", "value": 1}, {"name": "Polish Girl", "value": 2}]}, {"name": "Perfume Genius", "children": [{"name": "Valley", "value": 1}]}, {"name": "Peking Duk", "children": [{"name": "Take Me Over ", "value": 1}]}, {"name": "Kiiara", "children": [{"name": "Gold", "value": 1}, {"name": "Feels - Jai Wolf Remix", "value": 1}]}, {"name": "MisterWives", "children": [{"name": "Our Own House", "value": 1}]}, {"name": "Passion Pit", "children": [{"name": "Sleepyhead", "value": 2}, {"name": "Take a Walk", "value": 1}, {"name": "Little Secrets", "value": 1}, {"name": "Carried Away", "value": 1}, {"name": "Where the Sky Hangs", "value": 1}, {"name": "Whole Life Story", "value": 1}, {"name": "All I Want", "value": 1}, {"name": "Looks Like Rain", "value": 1}]}, {"name": "Smallpools", "children": [{"name": "Dreaming - The Chainsmokers Remix", "value": 3}]}, {"name": "Whethan", "children": [{"name": "Savage ", "value": 1}, {"name": "When Im Down", "value": 1}, {"name": "Stay Forever ", "value": 1}]}, {"name": "Hermitude", "children": [{"name": "HyperParadise - Flume Remix", "value": 1}, {"name": "The Buzz ", "value": 1}]}, {"name": "Miike Snow", "children": [{"name": "Genghis Khan - Louis the Child Remix", "value": 1}]}, {"name": "Joywave", "children": [{"name": "Nice House", "value": 1}]}, {"name": "The Postal Service", "children": [{"name": "The District Sleeps Alone Tonight", "value": 1}, {"name": "The District Sleeps Alone Tonight - Remastered", "value": 5}, {"name": "Such Great Heights - Remastered", "value": 6}, {"name": "Sleeping In - Remastered", "value": 10}, {"name": "Nothing Better", "value": 2}, {"name": "We Will Become Silhouettes - Remastered", "value": 3}, {"name": "Brand New Colony - Remastered", "value": 7}, {"name": "Clark Gable - Remastered", "value": 2}, {"name": "Recycled Air - Remastered", "value": 2}, {"name": "Against All Odds (Take a Look At Me Now) - Remastered", "value": 2}, {"name": "This Place Is a Prison - Remastered", "value": 2}, {"name": "Nothing Better - Remastered", "value": 1}, {"name": "Natural Anthem - Remastered", "value": 1}, {"name": "Turn Around", "value": 1}, {"name": "A Tattered Line of String", "value": 1}, {"name": "Be Still My Heart - Remastered", "value": 1}, {"name": "Theres Never Enough Time - Remastered", "value": 1}, {"name": "Suddenly Everything Has Changed - Remastered", "value": 1}, {"name": "Grow Old With Me - Remastered", "value": 1}, {"name": "Such Great Heights (John Tejada Remix) - Remastered", "value": 1}, {"name": "The District Sleeps Alone Tonight (DJ Downfall Persistent Beat Mix) - Remastered", "value": 1}, {"name": "Be Still My Heart (Nobody Remix) - Remastered", "value": 1}, {"name": "We Will Become Silhouettes (Matthew Dear Remix) - Remastered", "value": 1}, {"name": "Nothing Better (Styrofoam Remix) - Remastered", "value": 1}, {"name": "Recycled Air (Live on KEXP)", "value": 1}, {"name": "We Will Become Silhouettes (Performed by The Shins) - Remastered", "value": 2}, {"name": "Such Great Heights (Performed by Iron and Wine) - Remastered", "value": 1}]}, {"name": "ROLE MODEL", "children": [{"name": "i don\u2019t rly like u", "value": 1}, {"name": "play the part", "value": 1}]}, {"name": "Youth Lagoon", "children": [{"name": "17", "value": 1}]}, {"name": "Young the Giant", "children": [{"name": "Cough Syrup", "value": 2}, {"name": "Silvertongue", "value": 1}, {"name": "My Body", "value": 1}]}, {"name": "Vacationer", "children": [{"name": "Magnetism", "value": 1}]}, {"name": "Jay Som", "children": [{"name": "Rush", "value": 3}, {"name": "Baybee", "value": 8}, {"name": "One More Time, Please", "value": 5}, {"name": "I Think Youre Alright", "value": 3}, {"name": "The Bus Song", "value": 4}, {"name": "Superbike", "value": 7}, {"name": "If You Want It", "value": 6}, {"name": "Peace Out", "value": 6}, {"name": "Devotion", "value": 6}, {"name": "Nighttime Drive", "value": 6}, {"name": "Tenderness", "value": 9}, {"name": "Anak Ko", "value": 6}, {"name": "Crown", "value": 6}, {"name": "Get Well", "value": 8}, {"name": "Lipstick Stains", "value": 3}, {"name": "Remain", "value": 2}, {"name": "1 Billion Dogs", "value": 2}, {"name": "(BedHead)", "value": 2}, {"name": "Take It", "value": 2}, {"name": "Everybody Works", "value": 2}, {"name": "For Light", "value": 2}, {"name": "Our Red Door", "value": 1}, {"name": "Next To Me", "value": 1}, {"name": "A Thousand Words", "value": 2}, {"name": "Pirouette", "value": 1}, {"name": "Cant Sleep", "value": 1}]}, {"name": "Craft Spells", "children": [{"name": "After the Moment", "value": 1}]}, {"name": "Melodys Echo Chamber", "children": [{"name": "Breathe in, Breathe Out", "value": 1}, {"name": "I Follow You", "value": 1}, {"name": "Crystallized", "value": 1}, {"name": "You Wont Be Missing That Part of Me", "value": 1}, {"name": "Some Time Alone, Alone", "value": 1}, {"name": "Bisou Magique", "value": 1}, {"name": "Shirim", "value": 1}]}, {"name": "Pond", "children": [{"name": "Paint Me Silver", "value": 19}, {"name": "Sweep Me Off My Feet", "value": 16}, {"name": "30000 Megatons", "value": 4}, {"name": "Colder Than Ice", "value": 3}, {"name": "Edge Of The World Pt. 1", "value": 3}, {"name": "A/B", "value": 3}, {"name": "Waiting Around For Grace", "value": 4}, {"name": "Elvis Flaming Star", "value": 3}, {"name": "Holding Out For You", "value": 1}, {"name": "Zond", "value": 4}, {"name": "Heroic Shart", "value": 1}, {"name": "Sitting Up On Our Crane", "value": 1}, {"name": "Whatever Happened To The Million Head Collide?", "value": 1}, {"name": "Zen Automaton", "value": 1}, {"name": "All I Want For Xmas (Is A Tascam 388)", "value": 1}, {"name": "Edge Of The World Pt. 2", "value": 1}, {"name": "The Weather", "value": 14}, {"name": "Fire In The Water - Bonus Track", "value": 2}, {"name": "Daisy", "value": 1}, {"name": "Tasmania", "value": 1}, {"name": "Giant Tortoise", "value": 1}, {"name": "Medicine Hat", "value": 1}, {"name": "Man It Feels Like Space Again", "value": 1}]}, {"name": "The xx", "children": [{"name": "On Hold (Jamie xx Remix)", "value": 2}]}, {"name": "Poolside", "children": [{"name": "Harvest Moon", "value": 2}, {"name": "Kinda Lovely", "value": 1}]}, {"name": "The Temper Trap", "children": [{"name": "Love Lost", "value": 1}]}, {"name": "Great Good Fine OK", "children": [{"name": "Find Yourself", "value": 1}]}, {"name": "Charlie Burg", "children": [{"name": "Episode III", "value": 1}]}, {"name": "Blood Orange", "children": [{"name": "Charcoal Baby", "value": 6}, {"name": "Youre Not Good Enough", "value": 1}, {"name": "Saint", "value": 2}, {"name": "Champagne Coast", "value": 1}]}, {"name": "Elohim", "children": [{"name": "Fuck Your Money", "value": 1}]}, {"name": "Mothica", "children": [{"name": "Self-Destructive", "value": 1}]}, {"name": "Japanese Breakfast", "children": [{"name": "Boyish", "value": 2}, {"name": "Diving Woman", "value": 4}, {"name": "Road Head", "value": 9}, {"name": "Essentially", "value": 1}]}, {"name": "Cults", "children": [{"name": "Always Forever", "value": 1}]}, {"name": "Hippo Campus", "children": [{"name": "Simple Season", "value": 1}, {"name": "Way It Goes", "value": 2}, {"name": "Buttercup", "value": 1}, {"name": "Suicide Saturday", "value": 1}, {"name": "Bambi", "value": 1}]}, {"name": "Hot Chip", "children": [{"name": "The Warning", "value": 1}, {"name": "Hungry Child", "value": 1}, {"name": "Flutes", "value": 1}]}, {"name": "STRFKR", "children": [{"name": "Open Your Eyes", "value": 2}, {"name": "Kahlil Gibran", "value": 1}]}, {"name": "Broken Bells", "children": [{"name": "After the Disco", "value": 1}, {"name": "Good Luck", "value": 1}, {"name": "The High Road", "value": 1}]}, {"name": "Atlas Sound", "children": [{"name": "Walkabout (W/ Noah Lennox)", "value": 1}]}, {"name": "Chromeo", "children": [{"name": "Mustve Been ", "value": 1}]}, {"name": "Golden Vessel", "children": [{"name": "Shoulders", "value": 1}]}, {"name": "Sure Sure", "children": [{"name": "Lie Lie Lie", "value": 1}, {"name": "This Must Be The Place", "value": 1}]}, {"name": "Part Time", "children": [{"name": "I Can Help", "value": 2}, {"name": "Night Drive", "value": 1}, {"name": "Cassie (Won\u2019t You Be My Doll)", "value": 1}]}, {"name": "Elder Island", "children": [{"name": "The Big Unknown", "value": 2}, {"name": "Bamboo", "value": 1}, {"name": "What Its Worth", "value": 1}]}, {"name": "Justice", "children": [{"name": "D.A.N.C.E", "value": 6}]}, {"name": "HAIM", "children": [{"name": "Summer Girl - Bonus Track", "value": 3}, {"name": "The Steps", "value": 1}]}, {"name": "Metronomy", "children": [{"name": "Salted Caramel Ice Cream", "value": 1}]}, {"name": "Total Giovanni", "children": [{"name": "When We Break", "value": 1}]}, {"name": "Rhye", "children": [{"name": "Taste", "value": 2}]}, {"name": "Foals", "children": [{"name": "Inhaler", "value": 1}, {"name": "10,000 Feet", "value": 1}]}, {"name": "Joe Goddard", "children": [{"name": "Taking Over", "value": 1}]}, {"name": "DRAMA", "children": [{"name": "Dead and Gone", "value": 1}, {"name": "Nine One One", "value": 1}]}, {"name": "Little Dragon", "children": [{"name": "Timothy", "value": 4}, {"name": "Ritual Union", "value": 2}, {"name": "Twice", "value": 1}, {"name": "", "value": 1}, {"name": "Hold On", "value": 1}]}, {"name": "Yaeji", "children": [{"name": "One More", "value": 1}]}, {"name": "Jungle", "children": [{"name": "Casio", "value": 1}, {"name": "Lemonade Lake", "value": 1}]}, {"name": "Phantogram", "children": [{"name": "Dont Move", "value": 1}]}, {"name": "The Jungle Giants", "children": [{"name": "Heavy Hearted", "value": 13}, {"name": "Feel the Way I Do", "value": 1}, {"name": "Shes a Riot", "value": 2}]}, {"name": "Caribou", "children": [{"name": "Home", "value": 1}, {"name": "You and I", "value": 2}, {"name": "Never Come Back", "value": 1}, {"name": "Sister", "value": 1}, {"name": "Like I Loved You", "value": 1}]}, {"name": "Bombay Bicycle Club", "children": [{"name": "Eat, Sleep, Wake (Nothing But You) - Single Version", "value": 1}, {"name": "Racing Stripes", "value": 3}, {"name": "Everything Else Has Gone Wrong", "value": 2}, {"name": "Eat, Sleep, Wake (Nothing But You)", "value": 2}, {"name": "Always Like This", "value": 1}, {"name": "Shuffle", "value": 1}, {"name": "You Already Know", "value": 1}, {"name": "Emergency Contraception Blues", "value": 1}, {"name": "Lamplight", "value": 1}, {"name": "Evening / Morning", "value": 1}, {"name": "Dust On The Ground", "value": 1}, {"name": "Leave It", "value": 1}]}, {"name": "Miami Horror", "children": [{"name": "Leila - Poolside Remix", "value": 1}]}, {"name": "Bag Raiders", "children": [{"name": "Shooting Stars", "value": 2}]}, {"name": "Santigold", "children": [{"name": "Disparate Youth", "value": 1}, {"name": "Chasing Shadows", "value": 8}]}, {"name": "Peter Bjorn And John", "children": [{"name": "Young Folks", "value": 1}]}, {"name": "Ra Ra Riot", "children": [{"name": "Bad To Worse", "value": 1}]}, {"name": "R\u00dcF\u00dcS DU SOL", "children": [{"name": "Underwater", "value": 1}]}, {"name": "Jai Wolf", "children": [{"name": "Indian Summer", "value": 1}, {"name": "Lose My Mind ", "value": 1}, {"name": "Starlight", "value": 1}, {"name": "Lost ", "value": 1}]}, {"name": "ayokay", "children": [{"name": "Sleepless Nights", "value": 2}]}, {"name": "Crooked Colours", "children": [{"name": "Flow", "value": 1}]}, {"name": "Empire Of The Sun", "children": [{"name": "Walking On A Dream", "value": 1}]}, {"name": "Satin Jackets", "children": [{"name": "You Make Me Feel Good - Original Mix", "value": 1}]}, {"name": "Broods", "children": [{"name": "Peach", "value": 1}]}, {"name": "PNAU", "children": [{"name": "Solid Gold", "value": 1}]}, {"name": "Oneohtrix Point Never", "children": [{"name": "Babylon", "value": 5}]}, {"name": "Porches", "children": [{"name": "rangerover", "value": 1}, {"name": "Mood", "value": 1}]}, {"name": "TOPS", "children": [{"name": "Way to be Loved", "value": 2}, {"name": "Petals", "value": 1}, {"name": "Superstition Future", "value": 1}, {"name": "Witching Hour", "value": 2}, {"name": "The Hollow Sound of the Morning Chimes", "value": 1}, {"name": "I Feel Alive", "value": 1}, {"name": "Outside", "value": 1}, {"name": "Further", "value": 1}, {"name": "Seven Minutes", "value": 1}, {"name": "Evening", "value": 1}]}, {"name": "Anna of the North", "children": [{"name": "Lovers", "value": 1}]}, {"name": "Best Coast", "children": [{"name": "When Im With You", "value": 1}]}, {"name": "Yumi Zouma", "children": [{"name": "Southwark", "value": 1}, {"name": "Right Track / Wrong Man", "value": 1}]}, {"name": "Yves Tumor", "children": [{"name": "Kerosene!", "value": 1}]}, {"name": "Purity Ring", "children": [{"name": "stardew", "value": 1}]}, {"name": "Grimes", "children": [{"name": "Delete Forever", "value": 1}]}]}