{"name": "songData", "children": [{"name": "2017", "children": [{"name": "summer", "children": [{"name": "weekend", "value": 6}, {"name": "weekday", "value": 1}]}, {"name": "fall", "children": [{"name": "weekend", "value": 1}, {"name": "weekday", "value": 1}]}, {"name": "winter", "children": [{"name": "weekend", "value": 1}]}]}, {"name": "2018", "children": [{"name": "winter", "children": [{"name": "weekday", "value": 32}, {"name": "weekend", "value": 5}]}, {"name": "spring", "children": [{"name": "weekend", "value": 8}, {"name": "weekday", "value": 10}]}, {"name": "summer", "children": [{"name": "weekday", "value": 44}, {"name": "weekend", "value": 40}]}, {"name": "fall", "children": [{"name": "weekend", "value": 5}, {"name": "weekday", "value": 4}]}]}, {"name": "2019", "children": [{"name": "winter", "children": [{"name": "weekday", "value": 18}, {"name": "weekend", "value": 15}]}, {"name": "spring", "children": [{"name": "weekend", "value": 15}, {"name": "weekday", "value": 1}]}, {"name": "summer", "children": [{"name": "weekend", "value": 56}, {"name": "weekday", "value": 30}]}, {"name": "fall", "children": [{"name": "weekend", "value": 5}, {"name": "weekday", "value": 30}]}]}, {"name": "2020", "children": [{"name": "winter", "children": [{"name": "weekday", "value": 19}, {"name": "weekend", "value": 32}]}, {"name": "spring", "children": [{"name": "weekday", "value": 6}]}]}]}